MANIFEST.in
README.rst
setup.py
clifactory/__init__.py
clifactory/clifactory.py
clifactory.egg-info/PKG-INFO
clifactory.egg-info/SOURCES.txt
clifactory.egg-info/dependency_links.txt
clifactory.egg-info/pbr.json
clifactory.egg-info/top_level.txt