Metadata-Version: 1.1
Name: clifactory
Version: 0.1.1
Summary: Command line made as easy as a web app
Home-page: https://github.com/thomas-maurice/clifactory
Author: Thomas Maurice
Author-email: thomas@maurice.fr
License: WTFPL
Platform: any
Classifier: Development Status :: 3 - Alpha
Classifier: Environment :: Console
Classifier: Intended Audience :: Developers
Classifier: Topic :: Software Development :: Libraries :: Python Modules
Classifier: Programming Language :: Python :: 2.7
